{
  "_instructions": "Add your education and certifications here.",
  "sectionTitle": "Education & Certifications",
  "certificationsTitle": "Certifications",
  "education": [
    {
      "degree": "Master of Science",
      "institution": "University of Florida",
      "period": "Aug 2025 – Aug 2027",
      "description": "",
      "logo": "assets/images/logos/ufl.png",
      "color": "#FA4616"
    },
    {
      "degree": "Bachelor of Technology",
      "institution": "Parul University",
      "period": "Aug 2020 – May 2024",
      "description": "",
      "logo": "assets/images/logos/parul.png",
      "color": "#1A3C6E"
    }
  ],
  "certifications": [
    {
      "title": "Data Science Specialization",
      "issuer": "Johns Hopkins University",
      "date": "",
      "icon": "fas fa-certificate",
      "logo": "assets/images/logos/jhu.png",
      "color": "#002D72"
    },
    {
      "title": "Python Programming Masterclass",
      "issuer": "Udemy",
      "logo": "assets/images/logos/udemy.png",
      "date": "",
      "icon": "fas fa-certificate",
      "color": "#A435F0"
    },
    {
      "title": "AI Engineer Bootcamp",
      "issuer": "Udemy",
      "logo": "assets/images/logos/udemy.png",
      "date": "",
      "icon": "fas fa-certificate",
      "color": "#A435F0"
    },
    {
      "title": "Natural Language Processing using Python",
      "issuer": "Infosys Springboard",
      "logo": "assets/images/logos/infosys.png",
      "date": "",
      "icon": "fas fa-certificate",
      "color": "#007CC3"
    }
  ]
}
